{
  "name": "View",
  "engineVersion": "5.1.1",
  "engineSource": "Engine/Source/Runtime/Engine/Public/SceneView.h:835 (FViewUniformShaderParameters)",
  "layoutHash": "0x13BB15AA",
  "constantBufferSize": 5292,
  "bindingFlags": "StaticAndShader",
  "members": [
    {
      "offset": 0,
      "name": "TranslatedWorldToClip",
      "type": "Float4x4"
    },
    {
      "offset": 64,
      "name": "TranslatedWorldToSubpixelClip",
      "type": "Float4x4"
    },
    {
      "offset": 128,
      "name": "RelativeWorldToClip",
      "type": "Float4x4"
    },
    {
      "offset": 192,
      "name": "ClipToRelativeWorld",
      "type": "Float4x4"
    },
    {
      "offset": 256,
      "name": "TranslatedWorldToView",
      "type": "Float4x4"
    },
    {
      "offset": 320,
      "name": "ViewToTranslatedWorld",
      "type": "Float4x4"
    },
    {
      "offset": 384,
      "name": "TranslatedWorldToCameraView",
      "type": "Float4x4"
    },
    {
      "offset": 448,
      "name": "CameraViewToTranslatedWorld",
      "type": "Float4x4"
    },
    {
      "offset": 512,
      "name": "ViewToClip",
      "type": "Float4x4"
    },
    {
      "offset": 576,
      "name": "ViewToClipNoAA",
      "type": "Float4x4"
    },
    {
      "offset": 640,
      "name": "ClipToView",
      "type": "Float4x4"
    },
    {
      "offset": 704,
      "name": "ClipToTranslatedWorld",
      "type": "Float4x4"
    },
    {
      "offset": 768,
      "name": "SVPositionToTranslatedWorld",
      "type": "Float4x4"
    },
    {
      "offset": 832,
      "name": "ScreenToRelativeWorld",
      "type": "Float4x4"
    },
    {
      "offset": 896,
      "name": "ScreenToTranslatedWorld",
      "type": "Float4x4"
    },
    {
      "offset": 960,
      "name": "MobileMultiviewShadowTransform",
      "type": "Float4x4"
    },
    {
      "offset": 1024,
      "name": "ViewTilePosition",
      "type": "Float3"
    },
    {
      "offset": 1040,
      "name": "MatrixTilePosition",
      "type": "Float3"
    },
    {
      "offset": 1056,
      "name": "ViewForward",
      "type": "Float3"
    },
    {
      "offset": 1072,
      "name": "ViewUp",
      "type": "Float3"
    },
    {
      "offset": 1088,
      "name": "ViewRight",
      "type": "Float3"
    },
    {
      "offset": 1104,
      "name": "HMDViewNoRollUp",
      "type": "Float3"
    },
    {
      "offset": 1120,
      "name": "HMDViewNoRollRight",
      "type": "Float3"
    },
    {
      "offset": 1136,
      "name": "InvDeviceZToWorldZTransform",
      "type": "Float4"
    },
    {
      "offset": 1152,
      "name": "ScreenPositionScaleBias",
      "type": "Float4"
    },
    {
      "offset": 1168,
      "name": "RelativeWorldCameraOrigin",
      "type": "Float3"
    },
    {
      "offset": 1184,
      "name": "TranslatedWorldCameraOrigin",
      "type": "Float3"
    },
    {
      "offset": 1200,
      "name": "RelativeWorldViewOrigin",
      "type": "Float3"
    },
    {
      "offset": 1216,
      "name": "RelativePreViewTranslation",
      "type": "Float3"
    },
    {
      "offset": 1232,
      "name": "PrevViewToClip",
      "type": "Float4x4"
    },
    {
      "offset": 1296,
      "name": "PrevClipToView",
      "type": "Float4x4"
    },
    {
      "offset": 1360,
      "name": "PrevTranslatedWorldToClip",
      "type": "Float4x4"
    },
    {
      "offset": 1424,
      "name": "PrevTranslatedWorldToView",
      "type": "Float4x4"
    },
    {
      "offset": 1488,
      "name": "PrevViewToTranslatedWorld",
      "type": "Float4x4"
    },
    {
      "offset": 1552,
      "name": "PrevTranslatedWorldToCameraView",
      "type": "Float4x4"
    },
    {
      "offset": 1616,
      "name": "PrevCameraViewToTranslatedWorld",
      "type": "Float4x4"
    },
    {
      "offset": 1680,
      "name": "PrevTranslatedWorldCameraOrigin",
      "type": "Float3"
    },
    {
      "offset": 1696,
      "name": "PrevRelativeWorldCameraOrigin",
      "type": "Float3"
    },
    {
      "offset": 1712,
      "name": "PrevRelativeWorldViewOrigin",
      "type": "Float3"
    },
    {
      "offset": 1728,
      "name": "RelativePrevPreViewTranslation",
      "type": "Float3"
    },
    {
      "offset": 1744,
      "name": "PrevClipToRelativeWorld",
      "type": "Float4x4"
    },
    {
      "offset": 1808,
      "name": "PrevScreenToTranslatedWorld",
      "type": "Float4x4"
    },
    {
      "offset": 1872,
      "name": "ClipToPrevClip",
      "type": "Float4x4"
    },
    {
      "offset": 1936,
      "name": "ClipToPrevClipWithAA",
      "type": "Float4x4"
    },
    {
      "offset": 2000,
      "name": "TemporalAAJitter",
      "type": "Float4"
    },
    {
      "offset": 2016,
      "name": "GlobalClippingPlane",
      "type": "Float4"
    },
    {
      "offset": 2032,
      "name": "FieldOfViewWideAngles",
      "type": "Float2"
    },
    {
      "offset": 2040,
      "name": "PrevFieldOfViewWideAngles",
      "type": "Float2"
    },
    {
      "offset": 2048,
      "name": "ViewRectMin",
      "type": "Float4"
    },
    {
      "offset": 2064,
      "name": "ViewSizeAndInvSize",
      "type": "Float4"
    },
    {
      "offset": 2080,
      "name": "ViewRectMinAndSize",
      "type": "UInt4"
    },
    {
      "offset": 2096,
      "name": "LightProbeSizeRatioAndInvSizeRatio",
      "type": "Float4"
    },
    {
      "offset": 2112,
      "name": "BufferSizeAndInvSize",
      "type": "Float4"
    },
    {
      "offset": 2128,
      "name": "BufferBilinearUVMinMax",
      "type": "Float4"
    },
    {
      "offset": 2144,
      "name": "ScreenToViewSpace",
      "type": "Float4"
    },
    {
      "offset": 2160,
      "name": "BufferToSceneTextureScale",
      "type": "Float2"
    },
    {
      "offset": 2168,
      "name": "ResolutionFractionAndInv",
      "type": "Float2"
    },
    {
      "offset": 2176,
      "name": "NumSceneColorMSAASamples",
      "type": "Int"
    },
    {
      "offset": 2180,
      "name": "SeparateWaterMainDirLightLuminance",
      "type": "Float"
    },
    {
      "offset": 2184,
      "name": "PreExposure",
      "type": "Float"
    },
    {
      "offset": 2188,
      "name": "OneOverPreExposure",
      "type": "Float"
    },
    {
      "offset": 2192,
      "name": "DiffuseOverrideParameter",
      "type": "Float4"
    },
    {
      "offset": 2208,
      "name": "SpecularOverrideParameter",
      "type": "Float4"
    },
    {
      "offset": 2224,
      "name": "NormalOverrideParameter",
      "type": "Float4"
    },
    {
      "offset": 2240,
      "name": "RoughnessOverrideParameter",
      "type": "Float2"
    },
    {
      "offset": 2248,
      "name": "PrevFrameGameTime",
      "type": "Float"
    },
    {
      "offset": 2252,
      "name": "PrevFrameRealTime",
      "type": "Float"
    },
    {
      "offset": 2256,
      "name": "OutOfBoundsMask",
      "type": "Float"
    },
    {
      "offset": 2272,
      "name": "WorldCameraMovementSinceLastFrame",
      "type": "Float3"
    },
    {
      "offset": 2284,
      "name": "CullingSign",
      "type": "Float"
    },
    {
      "offset": 2288,
      "name": "NearPlane",
      "type": "Float"
    },
    {
      "offset": 2292,
      "name": "GameTime",
      "type": "Float"
    },
    {
      "offset": 2296,
      "name": "RealTime",
      "type": "Float"
    },
    {
      "offset": 2300,
      "name": "DeltaTime",
      "type": "Float"
    },
    {
      "offset": 2304,
      "name": "MaterialTextureMipBias",
      "type": "Float"
    },
    {
      "offset": 2308,
      "name": "MaterialTextureDerivativeMultiply",
      "type": "Float"
    },
    {
      "offset": 2312,
      "name": "Random",
      "type": "UInt"
    },
    {
      "offset": 2316,
      "name": "FrameNumber",
      "type": "UInt"
    },
    {
      "offset": 2320,
      "name": "StateFrameIndexMod8",
      "type": "UInt"
    },
    {
      "offset": 2324,
      "name": "StateFrameIndex",
      "type": "UInt"
    },
    {
      "offset": 2328,
      "name": "DebugViewModeMask",
      "type": "UInt"
    },
    {
      "offset": 2332,
      "name": "CameraCut",
      "type": "Float"
    },
    {
      "offset": 2336,
      "name": "UnlitViewmodeMask",
      "type": "Float"
    },
    {
      "offset": 2352,
      "name": "DirectionalLightColor",
      "type": "Float4"
    },
    {
      "offset": 2368,
      "name": "DirectionalLightDirection",
      "type": "Float3"
    },
    {
      "offset": 2384,
      "name": "TranslucencyLightingVolumeMin",
      "type": "Float4",
      "arraySize": 2
    },
    {
      "offset": 2416,
      "name": "TranslucencyLightingVolumeInvSize",
      "type": "Float4",
      "arraySize": 2
    },
    {
      "offset": 2448,
      "name": "TemporalAAParams",
      "type": "Float4"
    },
    {
      "offset": 2464,
      "name": "CircleDOFParams",
      "type": "Float4"
    },
    {
      "offset": 2480,
      "name": "DepthOfFieldSensorWidth",
      "type": "Float"
    },
    {
      "offset": 2484,
      "name": "DepthOfFieldFocalDistance",
      "type": "Float"
    },
    {
      "offset": 2488,
      "name": "DepthOfFieldScale",
      "type": "Float"
    },
    {
      "offset": 2492,
      "name": "DepthOfFieldFocalLength",
      "type": "Float"
    },
    {
      "offset": 2496,
      "name": "DepthOfFieldFocalRegion",
      "type": "Float"
    },
    {
      "offset": 2500,
      "name": "DepthOfFieldNearTransitionRegion",
      "type": "Float"
    },
    {
      "offset": 2504,
      "name": "DepthOfFieldFarTransitionRegion",
      "type": "Float"
    },
    {
      "offset": 2508,
      "name": "MotionBlurNormalizedToPixel",
      "type": "Float"
    },
    {
      "offset": 2512,
      "name": "GeneralPurposeTweak",
      "type": "Float"
    },
    {
      "offset": 2516,
      "name": "GeneralPurposeTweak2",
      "type": "Float"
    },
    {
      "offset": 2520,
      "name": "DemosaicVposOffset",
      "type": "Float"
    },
    {
      "offset": 2524,
      "name": "DecalDepthBias",
      "type": "Float"
    },
    {
      "offset": 2528,
      "name": "IndirectLightingColorScale",
      "type": "Float3"
    },
    {
      "offset": 2544,
      "name": "PrecomputedIndirectLightingColorScale",
      "type": "Float3"
    },
    {
      "offset": 2560,
      "name": "PrecomputedIndirectSpecularColorScale",
      "type": "Float3"
    },
    {
      "offset": 2576,
      "name": "AtmosphereLightDirection",
      "type": "Float4",
      "arraySize": 2
    },
    {
      "offset": 2608,
      "name": "AtmosphereLightIlluminanceOnGroundPostTransmittance",
      "type": "Float4",
      "arraySize": 2
    },
    {
      "offset": 2640,
      "name": "AtmosphereLightIlluminanceOuterSpace",
      "type": "Float4",
      "arraySize": 2
    },
    {
      "offset": 2672,
      "name": "AtmosphereLightDiscLuminance",
      "type": "Float4",
      "arraySize": 2
    },
    {
      "offset": 2704,
      "name": "AtmosphereLightDiscCosHalfApexAngle_PPTrans",
      "type": "Float4",
      "arraySize": 2
    },
    {
      "offset": 2736,
      "name": "SkyViewLutSizeAndInvSize",
      "type": "Float4"
    },
    {
      "offset": 2752,
      "name": "SkyCameraTranslatedWorldOrigin",
      "type": "Float3"
    },
    {
      "offset": 2768,
      "name": "SkyPlanetTranslatedWorldCenterAndViewHeight",
      "type": "Float4"
    },
    {
      "offset": 2784,
      "name": "SkyViewLutReferential",
      "type": "Float4x4"
    },
    {
      "offset": 2848,
      "name": "SkyAtmosphereSkyLuminanceFactor",
      "type": "Float4"
    },
    {
      "offset": 2864,
      "name": "SkyAtmospherePresentInScene",
      "type": "Float"
    },
    {
      "offset": 2868,
      "name": "SkyAtmosphereHeightFogContribution",
      "type": "Float"
    },
    {
      "offset": 2872,
      "name": "SkyAtmosphereBottomRadiusKm",
      "type": "Float"
    },
    {
      "offset": 2876,
      "name": "SkyAtmosphereTopRadiusKm",
      "type": "Float"
    },
    {
      "offset": 2880,
      "name": "SkyAtmosphereCameraAerialPerspectiveVolumeSizeAndInvSize",
      "type": "Float4"
    },
    {
      "offset": 2896,
      "name": "SkyAtmosphereAerialPerspectiveStartDepthKm",
      "type": "Float"
    },
    {
      "offset": 2900,
      "name": "SkyAtmosphereCameraAerialPerspectiveVolumeDepthResolution",
      "type": "Float"
    },
    {
      "offset": 2904,
      "name": "SkyAtmosphereCameraAerialPerspectiveVolumeDepthResolutionInv",
      "type": "Float"
    },
    {
      "offset": 2908,
      "name": "SkyAtmosphereCameraAerialPerspectiveVolumeDepthSliceLengthKm",
      "type": "Float"
    },
    {
      "offset": 2912,
      "name": "SkyAtmosphereCameraAerialPerspectiveVolumeDepthSliceLengthKmInv",
      "type": "Float"
    },
    {
      "offset": 2916,
      "name": "SkyAtmosphereApplyCameraAerialPerspectiveVolume",
      "type": "Float"
    },
    {
      "offset": 2928,
      "name": "NormalCurvatureToRoughnessScaleBias",
      "type": "Float3"
    },
    {
      "offset": 2940,
      "name": "RenderingReflectionCaptureMask",
      "type": "Float"
    },
    {
      "offset": 2944,
      "name": "RealTimeReflectionCapture",
      "type": "Float"
    },
    {
      "offset": 2948,
      "name": "RealTimeReflectionCapturePreExposure",
      "type": "Float"
    },
    {
      "offset": 2960,
      "name": "AmbientCubemapTint",
      "type": "Float4"
    },
    {
      "offset": 2976,
      "name": "AmbientCubemapIntensity",
      "type": "Float"
    },
    {
      "offset": 2980,
      "name": "SkyLightApplyPrecomputedBentNormalShadowingFlag",
      "type": "Float"
    },
    {
      "offset": 2984,
      "name": "SkyLightAffectReflectionFlag",
      "type": "Float"
    },
    {
      "offset": 2988,
      "name": "SkyLightAffectGlobalIlluminationFlag",
      "type": "Float"
    },
    {
      "offset": 2992,
      "name": "SkyLightColor",
      "type": "Float4"
    },
    {
      "offset": 3008,
      "name": "MobileSkyIrradianceEnvironmentMap",
      "type": "Float4",
      "arraySize": 8
    },
    {
      "offset": 3136,
      "name": "MobilePreviewMode",
      "type": "Float"
    },
    {
      "offset": 3140,
      "name": "HMDEyePaddingOffset",
      "type": "Float"
    },
    {
      "offset": 3144,
      "name": "ReflectionCubemapMaxMip",
      "type": "Float"
    },
    {
      "offset": 3148,
      "name": "ShowDecalsMask",
      "type": "Float"
    },
    {
      "offset": 3152,
      "name": "DistanceFieldAOSpecularOcclusionMode",
      "type": "UInt"
    },
    {
      "offset": 3156,
      "name": "IndirectCapsuleSelfShadowingIntensity",
      "type": "Float"
    },
    {
      "offset": 3168,
      "name": "ReflectionEnvironmentRoughnessMixingScaleBiasAndLargestWeight",
      "type": "Float3"
    },
    {
      "offset": 3180,
      "name": "StereoPassIndex",
      "type": "Int"
    },
    {
      "offset": 3184,
      "name": "GlobalVolumeCenterAndExtent",
      "type": "Float4",
      "arraySize": 6
    },
    {
      "offset": 3280,
      "name": "GlobalVolumeWorldToUVAddAndMul",
      "type": "Float4",
      "arraySize": 6
    },
    {
      "offset": 3376,
      "name": "GlobalDistanceFieldMipWorldToUVScale",
      "type": "Float4",
      "arraySize": 6
    },
    {
      "offset": 3472,
      "name": "GlobalDistanceFieldMipWorldToUVBias",
      "type": "Float4",
      "arraySize": 6
    },
    {
      "offset": 3568,
      "name": "GlobalDistanceFieldMipFactor",
      "type": "Float"
    },
    {
      "offset": 3572,
      "name": "GlobalDistanceFieldMipTransition",
      "type": "Float"
    },
    {
      "offset": 3576,
      "name": "GlobalDistanceFieldClipmapSizeInPages",
      "type": "Int"
    },
    {
      "offset": 3584,
      "name": "GlobalDistanceFieldInvPageAtlasSize",
      "type": "Float3"
    },
    {
      "offset": 3600,
      "name": "GlobalDistanceFieldInvCoverageAtlasSize",
      "type": "Float3"
    },
    {
      "offset": 3612,
      "name": "GlobalVolumeDimension",
      "type": "Float"
    },
    {
      "offset": 3616,
      "name": "GlobalVolumeTexelSize",
      "type": "Float"
    },
    {
      "offset": 3620,
      "name": "MaxGlobalDFAOConeDistance",
      "type": "Float"
    },
    {
      "offset": 3624,
      "name": "NumGlobalSDFClipmaps",
      "type": "UInt"
    },
    {
      "offset": 3628,
      "name": "CoveredExpandSurfaceScale",
      "type": "Float"
    },
    {
      "offset": 3632,
      "name": "NotCoveredExpandSurfaceScale",
      "type": "Float"
    },
    {
      "offset": 3636,
      "name": "NotCoveredMinStepScale",
      "type": "Float"
    },
    {
      "offset": 3640,
      "name": "DitheredTransparencyStepThreshold",
      "type": "Float"
    },
    {
      "offset": 3644,
      "name": "DitheredTransparencyTraceThreshold",
      "type": "Float"
    },
    {
      "offset": 3648,
      "name": "CursorPosition",
      "type": "Int2"
    },
    {
      "offset": 3656,
      "name": "bCheckerboardSubsurfaceProfileRendering",
      "type": "Float"
    },
    {
      "offset": 3664,
      "name": "VolumetricFogInvGridSize",
      "type": "Float3"
    },
    {
      "offset": 3680,
      "name": "VolumetricFogGridZParams",
      "type": "Float3"
    },
    {
      "offset": 3696,
      "name": "VolumetricFogSVPosToVolumeUV",
      "type": "Float2"
    },
    {
      "offset": 3704,
      "name": "VolumetricFogMaxDistance",
      "type": "Float"
    },
    {
      "offset": 3712,
      "name": "VolumetricLightmapWorldToUVScale",
      "type": "Float3"
    },
    {
      "offset": 3728,
      "name": "VolumetricLightmapWorldToUVAdd",
      "type": "Float3"
    },
    {
      "offset": 3744,
      "name": "VolumetricLightmapIndirectionTextureSize",
      "type": "Float3"
    },
    {
      "offset": 3756,
      "name": "VolumetricLightmapBrickSize",
      "type": "Float"
    },
    {
      "offset": 3760,
      "name": "VolumetricLightmapBrickTexelSize",
      "type": "Float3"
    },
    {
      "offset": 3772,
      "name": "IndirectLightingCacheShowFlag",
      "type": "Float"
    },
    {
      "offset": 3776,
      "name": "EyeToPixelSpreadAngle",
      "type": "Float"
    },
    {
      "offset": 3792,
      "name": "XRPassthroughCameraUVs",
      "type": "Float4",
      "arraySize": 2
    },
    {
      "offset": 3824,
      "name": "GlobalVirtualTextureMipBias",
      "type": "Float"
    },
    {
      "offset": 3828,
      "name": "VirtualTextureFeedbackShift",
      "type": "UInt"
    },
    {
      "offset": 3832,
      "name": "VirtualTextureFeedbackMask",
      "type": "UInt"
    },
    {
      "offset": 3836,
      "name": "VirtualTextureFeedbackStride",
      "type": "UInt"
    },
    {
      "offset": 3840,
      "name": "VirtualTextureFeedbackJitterOffset",
      "type": "UInt"
    },
    {
      "offset": 3844,
      "name": "VirtualTextureFeedbackSampleOffset",
      "type": "UInt"
    },
    {
      "offset": 3856,
      "name": "RuntimeVirtualTextureMipLevel",
      "type": "Float4"
    },
    {
      "offset": 3872,
      "name": "RuntimeVirtualTexturePackHeight",
      "type": "Float2"
    },
    {
      "offset": 3888,
      "name": "RuntimeVirtualTextureDebugParams",
      "type": "Float4"
    },
    {
      "offset": 3904,
      "name": "OverrideLandscapeLOD",
      "type": "Float"
    },
    {
      "offset": 3908,
      "name": "FarShadowStaticMeshLODBias",
      "type": "Int"
    },
    {
      "offset": 3912,
      "name": "MinRoughness",
      "type": "Float"
    },
    {
      "offset": 3920,
      "name": "HairRenderInfo",
      "type": "Float4"
    },
    {
      "offset": 3936,
      "name": "EnableSkyLight",
      "type": "UInt"
    },
    {
      "offset": 3940,
      "name": "HairRenderInfoBits",
      "type": "UInt"
    },
    {
      "offset": 3944,
      "name": "HairComponents",
      "type": "UInt"
    },
    {
      "offset": 3948,
      "name": "bSubsurfacePostprocessEnabled",
      "type": "Float"
    },
    {
      "offset": 3952,
      "name": "SSProfilesTextureSizeAndInvSize",
      "type": "Float4"
    },
    {
      "offset": 3968,
      "name": "SSProfilesPreIntegratedTextureSizeAndInvSize",
      "type": "Float4"
    },
    {
      "offset": 3984,
      "name": "PhysicsFieldClipmapCenter",
      "type": "Float3"
    },
    {
      "offset": 3996,
      "name": "PhysicsFieldClipmapDistance",
      "type": "Float"
    },
    {
      "offset": 4000,
      "name": "PhysicsFieldClipmapResolution",
      "type": "Int"
    },
    {
      "offset": 4004,
      "name": "PhysicsFieldClipmapExponent",
      "type": "Int"
    },
    {
      "offset": 4008,
      "name": "PhysicsFieldClipmapCount",
      "type": "Int"
    },
    {
      "offset": 4012,
      "name": "PhysicsFieldTargetCount",
      "type": "Int"
    },
    {
      "offset": 4016,
      "name": "PhysicsFieldTargets",
      "type": "Int4",
      "arraySize": 32
    },
    {
      "offset": 4528,
      "name": "InstanceSceneDataSOAStride",
      "type": "UInt"
    },
    {
      "offset": 4532,
      "name": "GPUSceneViewId",
      "type": "UInt"
    },
    {
      "offset": 4536,
      "name": "ViewResolutionFraction",
      "type": "Float"
    },
    {
      "offset": 4540,
      "name": "SubSurfaceColorAsTransmittanceAtDistanceInMeters",
      "type": "Float"
    },
    {
      "offset": 5056,
      "name": "bShadingEnergyConservation",
      "type": "UInt"
    },
    {
      "offset": 5060,
      "name": "bShadingEnergyPreservation",
      "type": "UInt"
    },
    {
      "offset": 5168,
      "name": "RectLightAtlasSizeAndInvSize",
      "type": "Float4"
    },
    {
      "offset": 5184,
      "name": "RectLightAtlasMaxMipLevel",
      "type": "Float"
    },
    {
      "offset": 5264,
      "name": "TLASRelativePreViewTranslation",
      "type": "Float3"
    },
    {
      "offset": 5280,
      "name": "TLASViewTilePosition",
      "type": "Float3"
    }
  ],
  "resources": [
    {
      "index": 0,
      "offset": 4544,
      "name": "MaterialTextureBilinearWrapedSampler",
      "type": "UBMT_SAMPLER"
    },
    {
      "index": 1,
      "offset": 4552,
      "name": "MaterialTextureBilinearClampedSampler",
      "type": "UBMT_SAMPLER"
    },
    {
      "index": 2,
      "offset": 4560,
      "name": "VolumetricLightmapIndirectionTexture",
      "type": "UBMT_TEXTURE"
    },
    {
      "index": 3,
      "offset": 4568,
      "name": "VolumetricLightmapBrickAmbientVector",
      "type": "UBMT_TEXTURE"
    },
    {
      "index": 4,
      "offset": 4576,
      "name": "VolumetricLightmapBrickSHCoefficients0",
      "type": "UBMT_TEXTURE"
    },
    {
      "index": 5,
      "offset": 4584,
      "name": "VolumetricLightmapBrickSHCoefficients1",
      "type": "UBMT_TEXTURE"
    },
    {
      "index": 6,
      "offset": 4592,
      "name": "VolumetricLightmapBrickSHCoefficients2",
      "type": "UBMT_TEXTURE"
    },
    {
      "index": 7,
      "offset": 4600,
      "name": "VolumetricLightmapBrickSHCoefficients3",
      "type": "UBMT_TEXTURE"
    },
    {
      "index": 8,
      "offset": 4608,
      "name": "VolumetricLightmapBrickSHCoefficients4",
      "type": "UBMT_TEXTURE"
    },
    {
      "index": 9,
      "offset": 4616,
      "name": "VolumetricLightmapBrickSHCoefficients5",
      "type": "UBMT_TEXTURE"
    },
    {
      "index": 10,
      "offset": 4624,
      "name": "SkyBentNormalBrickTexture",
      "type": "UBMT_TEXTURE"
    },
    {
      "index": 11,
      "offset": 4632,
      "name": "DirectionalLightShadowingBrickTexture",
      "type": "UBMT_TEXTURE"
    },
    {
      "index": 12,
      "offset": 4640,
      "name": "VolumetricLightmapBrickAmbientVectorSampler",
      "type": "UBMT_SAMPLER"
    },
    {
      "index": 13,
      "offset": 4648,
      "name": "VolumetricLightmapTextureSampler0",
      "type": "UBMT_SAMPLER"
    },
    {
      "index": 14,
      "offset": 4656,
      "name": "VolumetricLightmapTextureSampler1",
      "type": "UBMT_SAMPLER"
    },
    {
      "index": 15,
      "offset": 4664,
      "name": "VolumetricLightmapTextureSampler2",
      "type": "UBMT_SAMPLER"
    },
    {
      "index": 16,
      "offset": 4672,
      "name": "VolumetricLightmapTextureSampler3",
      "type": "UBMT_SAMPLER"
    },
    {
      "index": 17,
      "offset": 4680,
      "name": "VolumetricLightmapTextureSampler4",
      "type": "UBMT_SAMPLER"
    },
    {
      "index": 18,
      "offset": 4688,
      "name": "VolumetricLightmapTextureSampler5",
      "type": "UBMT_SAMPLER"
    },
    {
      "index": 19,
      "offset": 4696,
      "name": "SkyBentNormalTextureSampler",
      "type": "UBMT_SAMPLER"
    },
    {
      "index": 20,
      "offset": 4704,
      "name": "DirectionalLightShadowingTextureSampler",
      "type": "UBMT_SAMPLER"
    },
    {
      "index": 21,
      "offset": 4712,
      "name": "GlobalDistanceFieldPageAtlasTexture",
      "type": "UBMT_TEXTURE"
    },
    {
      "index": 22,
      "offset": 4720,
      "name": "GlobalDistanceFieldCoverageAtlasTexture",
      "type": "UBMT_TEXTURE"
    },
    {
      "index": 23,
      "offset": 4728,
      "name": "GlobalDistanceFieldPageTableTexture",
      "type": "UBMT_TEXTURE"
    },
    {
      "index": 24,
      "offset": 4736,
      "name": "GlobalDistanceFieldMipTexture",
      "type": "UBMT_TEXTURE"
    },
    {
      "index": 25,
      "offset": 4744,
      "name": "AtmosphereTransmittanceTexture",
      "type": "UBMT_TEXTURE"
    },
    {
      "index": 26,
      "offset": 4752,
      "name": "AtmosphereTransmittanceTextureSampler",
      "type": "UBMT_SAMPLER"
    },
    {
      "index": 27,
      "offset": 4760,
      "name": "AtmosphereIrradianceTexture",
      "type": "UBMT_TEXTURE"
    },
    {
      "index": 28,
      "offset": 4768,
      "name": "AtmosphereIrradianceTextureSampler",
      "type": "UBMT_SAMPLER"
    },
    {
      "index": 29,
      "offset": 4776,
      "name": "AtmosphereInscatterTexture",
      "type": "UBMT_TEXTURE"
    },
    {
      "index": 30,
      "offset": 4784,
      "name": "AtmosphereInscatterTextureSampler",
      "type": "UBMT_SAMPLER"
    },
    {
      "index": 31,
      "offset": 4792,
      "name": "PerlinNoiseGradientTexture",
      "type": "UBMT_TEXTURE"
    },
    {
      "index": 32,
      "offset": 4800,
      "name": "PerlinNoiseGradientTextureSampler",
      "type": "UBMT_SAMPLER"
    },
    {
      "index": 33,
      "offset": 4808,
      "name": "PerlinNoise3DTexture",
      "type": "UBMT_TEXTURE"
    },
    {
      "index": 34,
      "offset": 4816,
      "name": "PerlinNoise3DTextureSampler",
      "type": "UBMT_SAMPLER"
    },
    {
      "index": 35,
      "offset": 4824,
      "name": "SobolSamplingTexture",
      "type": "UBMT_TEXTURE"
    },
    {
      "index": 36,
      "offset": 4832,
      "name": "SharedPointWrappedSampler",
      "type": "UBMT_SAMPLER"
    },
    {
      "index": 37,
      "offset": 4840,
      "name": "SharedPointClampedSampler",
      "type": "UBMT_SAMPLER"
    },
    {
      "index": 38,
      "offset": 4848,
      "name": "SharedBilinearWrappedSampler",
      "type": "UBMT_SAMPLER"
    },
    {
      "index": 39,
      "offset": 4856,
      "name": "SharedBilinearClampedSampler",
      "type": "UBMT_SAMPLER"
    },
    {
      "index": 40,
      "offset": 4864,
      "name": "SharedBilinearAnisoClampedSampler",
      "type": "UBMT_SAMPLER"
    },
    {
      "index": 41,
      "offset": 4872,
      "name": "SharedTrilinearWrappedSampler",
      "type": "UBMT_SAMPLER"
    },
    {
      "index": 42,
      "offset": 4880,
      "name": "SharedTrilinearClampedSampler",
      "type": "UBMT_SAMPLER"
    },
    {
      "index": 43,
      "offset": 4888,
      "name": "PreIntegratedBRDF",
      "type": "UBMT_TEXTURE"
    },
    {
      "index": 44,
      "offset": 4896,
      "name": "PreIntegratedBRDFSampler",
      "type": "UBMT_SAMPLER"
    },
    {
      "index": 45,
      "offset": 4904,
      "name": "PrimitiveSceneData",
      "type": "UBMT_SRV"
    },
    {
      "index": 46,
      "offset": 4912,
      "name": "InstanceSceneData",
      "type": "UBMT_SRV"
    },
    {
      "index": 47,
      "offset": 4920,
      "name": "InstancePayloadData",
      "type": "UBMT_SRV"
    },
    {
      "index": 48,
      "offset": 4928,
      "name": "LightmapSceneData",
      "type": "UBMT_SRV"
    },
    {
      "index": 49,
      "offset": 4936,
      "name": "SkyIrradianceEnvironmentMap",
      "type": "UBMT_SRV"
    },
    {
      "index": 50,
      "offset": 4944,
      "name": "TransmittanceLutTexture",
      "type": "UBMT_TEXTURE"
    },
    {
      "index": 51,
      "offset": 4952,
      "name": "TransmittanceLutTextureSampler",
      "type": "UBMT_SAMPLER"
    },
    {
      "index": 52,
      "offset": 4960,
      "name": "SkyViewLutTexture",
      "type": "UBMT_TEXTURE"
    },
    {
      "index": 53,
      "offset": 4968,
      "name": "SkyViewLutTextureSampler",
      "type": "UBMT_SAMPLER"
    },
    {
      "index": 54,
      "offset": 4976,
      "name": "DistantSkyLightLutTexture",
      "type": "UBMT_TEXTURE"
    },
    {
      "index": 55,
      "offset": 4984,
      "name": "DistantSkyLightLutTextureSampler",
      "type": "UBMT_SAMPLER"
    },
    {
      "index": 56,
      "offset": 4992,
      "name": "CameraAerialPerspectiveVolume",
      "type": "UBMT_TEXTURE"
    },
    {
      "index": 57,
      "offset": 5000,
      "name": "CameraAerialPerspectiveVolumeSampler",
      "type": "UBMT_SAMPLER"
    },
    {
      "index": 58,
      "offset": 5008,
      "name": "HairScatteringLUTTexture",
      "type": "UBMT_TEXTURE"
    },
    {
      "index": 59,
      "offset": 5016,
      "name": "HairScatteringLUTSampler",
      "type": "UBMT_SAMPLER"
    },
    {
      "index": 60,
      "offset": 5024,
      "name": "LTCMatTexture",
      "type": "UBMT_TEXTURE"
    },
    {
      "index": 61,
      "offset": 5032,
      "name": "LTCMatSampler",
      "type": "UBMT_SAMPLER"
    },
    {
      "index": 62,
      "offset": 5040,
      "name": "LTCAmpTexture",
      "type": "UBMT_TEXTURE"
    },
    {
      "index": 63,
      "offset": 5048,
      "name": "LTCAmpSampler",
      "type": "UBMT_SAMPLER"
    },
    {
      "index": 64,
      "offset": 5064,
      "name": "ShadingEnergyGGXSpecTexture",
      "type": "UBMT_TEXTURE"
    },
    {
      "index": 65,
      "offset": 5072,
      "name": "ShadingEnergyGGXGlassTexture",
      "type": "UBMT_TEXTURE"
    },
    {
      "index": 66,
      "offset": 5080,
      "name": "ShadingEnergyClothSpecTexture",
      "type": "UBMT_TEXTURE"
    },
    {
      "index": 67,
      "offset": 5088,
      "name": "ShadingEnergyDiffuseTexture",
      "type": "UBMT_TEXTURE"
    },
    {
      "index": 68,
      "offset": 5096,
      "name": "ShadingEnergySampler",
      "type": "UBMT_SAMPLER"
    },
    {
      "index": 69,
      "offset": 5104,
      "name": "SSProfilesTexture",
      "type": "UBMT_TEXTURE"
    },
    {
      "index": 70,
      "offset": 5112,
      "name": "SSProfilesSampler",
      "type": "UBMT_SAMPLER"
    },
    {
      "index": 71,
      "offset": 5120,
      "name": "SSProfilesTransmissionSampler",
      "type": "UBMT_SAMPLER"
    },
    {
      "index": 72,
      "offset": 5128,
      "name": "SSProfilesPreIntegratedTexture",
      "type": "UBMT_TEXTURE"
    },
    {
      "index": 73,
      "offset": 5136,
      "name": "SSProfilesPreIntegratedSampler",
      "type": "UBMT_SAMPLER"
    },
    {
      "index": 74,
      "offset": 5144,
      "name": "WaterIndirection",
      "type": "UBMT_SRV"
    },
    {
      "index": 75,
      "offset": 5152,
      "name": "WaterData",
      "type": "UBMT_SRV"
    },
    {
      "index": 76,
      "offset": 5192,
      "name": "RectLightAtlasTexture",
      "type": "UBMT_TEXTURE"
    },
    {
      "index": 77,
      "offset": 5200,
      "name": "RectLightAtlasSampler",
      "type": "UBMT_SAMPLER"
    },
    {
      "index": 78,
      "offset": 5208,
      "name": "LandscapeWeightmapSampler",
      "type": "UBMT_SAMPLER"
    },
    {
      "index": 79,
      "offset": 5216,
      "name": "LandscapeIndirection",
      "type": "UBMT_SRV"
    },
    {
      "index": 80,
      "offset": 5224,
      "name": "LandscapePerComponentData",
      "type": "UBMT_SRV"
    },
    {
      "index": 81,
      "offset": 5232,
      "name": "VTFeedbackBuffer",
      "type": "UBMT_UAV"
    },
    {
      "index": 82,
      "offset": 5240,
      "name": "EditorVisualizeLevelInstanceIds",
      "type": "UBMT_SRV"
    },
    {
      "index": 83,
      "offset": 5248,
      "name": "EditorSelectedHitProxyIds",
      "type": "UBMT_SRV"
    },
    {
      "index": 84,
      "offset": 5256,
      "name": "PhysicsFieldClipmapBuffer",
      "type": "UBMT_SRV"
    }
  ]
}
